rbloom-1.5.4.dist-info/METADATA
rbloom-1.5.4.dist-info/WHEEL
rbloom-1.5.4.dist-info/licenses/LICENSE
rbloom/__init__.py
rbloom/__init__.pyi
rbloom/py.typed
rbloom/rbloom.pyd
rbloom-1.5.4.dist-info/RECORD
